setup.py
otterop/lang/array.py
otterop/lang/error.py
otterop/lang/result.py
otterop/lang/string.py
otterop_lang-0.2.0.dist-info/METADATA
otterop_lang-0.2.0.dist-info/WHEEL
otterop_lang-0.2.0.dist-info/RECORD
