Metadata-Version: 2.1
Name: otterop-lang
Version: 0.2.0
Summary: OtterOP lang
Author-email: Emanuele Sabellico <emasab@gmail.com>
Requires-Python: >=3.7
